configrender/__init__.py
configrender/render.py
configrender-1.0.5.dist-info/DESCRIPTION.rst
configrender-1.0.5.dist-info/METADATA
configrender-1.0.5.dist-info/RECORD
configrender-1.0.5.dist-info/WHEEL
configrender-1.0.5.dist-info/entry_points.txt
configrender-1.0.5.dist-info/metadata.json
configrender-1.0.5.dist-info/top_level.txt
