Metadata-Version: 2.0
Name: configrender
Version: 1.0.5
Summary: Config Render
Home-page: https://dev.afon.ninja/
Author: afon
Author-email: me@afon.ninja
License: MIT
Platform: UNKNOWN
Classifier: Development Status :: 5 - Production/Stable
Classifier: Intended Audience :: Developers
Classifier: License :: OSI Approved :: MIT License
Classifier: Operating System :: OS Independent
Classifier: Programming Language :: Python
Classifier: Programming Language :: Python :: 3
Classifier: Programming Language :: Python :: 3.6
Classifier: Programming Language :: Python :: Implementation :: PyPy
Classifier: Topic :: Software Development :: Libraries :: Python Modules
Requires-Dist: Jinja2 (>=2.10)
Requires-Dist: PyYAML (>=3.12)
